activities/__init__.py
activities/booking.py
activities/constants.py
ui_booking.com-0.102.dist-info/METADATA
ui_booking.com-0.102.dist-info/WHEEL
ui_booking.com-0.102.dist-info/top_level.txt
ui_booking.com-0.102.dist-info/RECORD
