Metadata-Version: 2.1
Name: ui-booking.com
Version: 0.102
Summary: Second release of my package
Author: Arijit Das
